{"GFSOSO.js": {"label": "GFSOSO", "lastUpdated": "2020-02-27 05:59:48"}, "Nlc.cn.js": {"label": "nlc.cn", "lastUpdated": "2020-12-28 03:38:46"}, "PatentStar.js": {"label": "PatentStar", "lastUpdated": "2021-04-14 12:46:00"}, "Soopat.js": {"label": "Soopat", "lastUpdated": "2020-03-18 06:28:12"}, "SuperLib.js": {"label": "SuperLib", "lastUpdated": "2020-12-13 12:49:28"}, "CNKI.js": {"label": "CNKI", "lastUpdated": "2022-10-11 12:51:15"}, "Duxiu.js": {"label": "Duxiu", "lastUpdated": "2022-06-29 02:01:12"}, "ProQuestCN Thesis.js": {"label": "ProQuestCN Thesis", "lastUpdated": "2020-09-07 01:24:40"}, "Douban.js": {"label": "Douban", "lastUpdated": "2022-04-14 09:59:01"}, "Weixin.js": {"label": "Weixin", "lastUpdated": "2021-03-01 04:36:11"}, "Wenjin.js": {"label": "Wenjin", "lastUpdated": "2020-08-29 14:11:42"}, "Spc.org.cn.js": {"label": "\u4e2d\u56fd\u6807\u51c6\u5728\u7ebf\u670d\u52a1\u7f51", "lastUpdated": "2022-10-03 15:51:14"}, "Dangdang.js": {"label": "Dangdang", "lastUpdated": "2022-01-24 06:22:02"}, "Jd.js": {"label": "Jd", "lastUpdated": "2021-03-25 10:51:26"}, "Zhihu.js": {"label": "Zhihu", "lastUpdated": "2021-09-19 21:51:07"}, "Ncpssd.js": {"label": "Ncpssd", "lastUpdated": "2020-08-08 23:03:26"}, "xiaoyuzhoufm.js": {"label": "xiaoyuzhoufm", "lastUpdated": "2022-04-10 15:23:58"}, "Baidu Scholar.js": {"label": "Baidu Scholar", "lastUpdated": "2021-12-28 04:27:11"}, "BiliBili.js": {"label": "BiliBili", "lastUpdated": "2020-12-19 07:48:50"}, "WeiPu.js": {"label": "WeiPu", "lastUpdated": "2019-12-13 09:03:39"}, "dpaper.js": {"label": "dpaper", "lastUpdated": "2022-06-29 01:57:00"}, "Wanfang Data.js": {"label": "Wanfang Data", "lastUpdated": "2022-10-14 07:25:40"}}